mlflow_oidc_auth/__init__.py
mlflow_oidc_auth/app.py
mlflow_oidc_auth/auth.py
mlflow_oidc_auth/cli.py
mlflow_oidc_auth/config.py
mlflow_oidc_auth/dependencies.py
mlflow_oidc_auth/entities.py
mlflow_oidc_auth/exceptions.py
mlflow_oidc_auth/hack.py
mlflow_oidc_auth/logger.py
mlflow_oidc_auth/oauth.py
mlflow_oidc_auth/permissions.py
mlflow_oidc_auth/sqlalchemy_store.py
mlflow_oidc_auth/store.py
mlflow_oidc_auth/user.py
mlflow_oidc_auth/bridge/__init__.py
mlflow_oidc_auth/bridge/user.py
mlflow_oidc_auth/config_providers/__init__.py
mlflow_oidc_auth/config_providers/aws_parameter_store_provider.py
mlflow_oidc_auth/config_providers/aws_secrets_provider.py
mlflow_oidc_auth/config_providers/azure_keyvault_provider.py
mlflow_oidc_auth/config_providers/base.py
mlflow_oidc_auth/config_providers/env_provider.py
mlflow_oidc_auth/config_providers/kubernetes_provider.py
mlflow_oidc_auth/config_providers/manager.py
mlflow_oidc_auth/config_providers/mlflow_env.py
mlflow_oidc_auth/config_providers/vault_provider.py
mlflow_oidc_auth/db/__init__.py
mlflow_oidc_auth/db/cli.py
mlflow_oidc_auth/db/models.py
mlflow_oidc_auth/db/utils.py
mlflow_oidc_auth/db/migrations/__init__.py
mlflow_oidc_auth/db/migrations/alembic.ini
mlflow_oidc_auth/db/migrations/env.py
mlflow_oidc_auth/db/migrations/versions/0565cf04c12e_token_expiration.py
mlflow_oidc_auth/db/migrations/versions/1ddf23934b63_add_regex_permissions.py
mlflow_oidc_auth/db/migrations/versions/2d5d40dd803f_add_user_groups.py
mlflow_oidc_auth/db/migrations/versions/3c3272527ade_scorer_permissions.py
mlflow_oidc_auth/db/migrations/versions/4ab210836965_add_group_permissions.py
mlflow_oidc_auth/db/migrations/versions/8606fa83a998_initial_migration.py
mlflow_oidc_auth/db/migrations/versions/8c1cf75c5314_add_service_accounts.py
mlflow_oidc_auth/db/migrations/versions/913635c83867_add_prompt.py
mlflow_oidc_auth/db/migrations/versions/__init__.py
mlflow_oidc_auth/graphql/__init__.py
mlflow_oidc_auth/graphql/middleware.py
mlflow_oidc_auth-6.1.1.dist-info/licenses/LICENSE
mlflow_oidc_auth-6.1.1.dist-info/METADATA
mlflow_oidc_auth-6.1.1.dist-info/WHEEL
mlflow_oidc_auth-6.1.1.dist-info/entry_points.txt
mlflow_oidc_auth-6.1.1.dist-info/top_level.txt
mlflow_oidc_auth-6.1.1.dist-info/RECORD
