Metadata-Version: 2.4
Name: mlflow-oidc-auth
Version: 6.1.1
Summary: OIDC auth plugin for MLflow
Maintainer-email: Alexander Kharkevich <alex@kharkevich.org>
License-Expression: Apache-2.0
Project-URL: homepage, https://github.com/mlflow-oidc/mlflow-oidc-auth
Project-URL: issues, https://github.com/mlflow-oidc/mlflow-oidc-auth/issues
Project-URL: documentation, https://github.com/mlflow-oidc/mlflow-oidc-auth/tree/main/docs/
Project-URL: repository, https://github.com/mlflow-oidc/mlflow-oidc-auth
Keywords: mlflow,oauth2,oidc
Classifier: Development Status :: 5 - Production/Stable
Classifier: Intended Audience :: Developers
Classifier: Intended Audience :: End Users/Desktop
Classifier: Intended Audience :: Science/Research
Classifier: Intended Audience :: Information Technology
Classifier: Topic :: Scientific/Engineering :: Artificial Intelligence
Classifier: Topic :: Software Development :: Libraries :: Python Modules
Classifier: Operating System :: OS Independent
Classifier: Programming Language :: Python :: 3.10
Requires-Python: >=3.10
License-File: LICENSE
Requires-Dist: mlflow<4,>=3.8.1
Requires-Dist: python-dotenv<2
Requires-Dist: requests<3,>=2.31.0
Requires-Dist: sqlalchemy<3,>=1.4.0
Requires-Dist: flask<4
Requires-Dist: gunicorn<24; platform_system != "Windows"
Requires-Dist: alembic!=1.10.0,<2
Requires-Dist: authlib<2
Requires-Dist: uvicorn>=0.20.0
Requires-Dist: fastapi>=0.100.0
Requires-Dist: asgiref>=3.0.0
Requires-Dist: httpx>=0.28.1
Provides-Extra: dev
Requires-Dist: black<26,>=24.8.0; extra == "dev"
Requires-Dist: pytest<9,>=8.3.2; extra == "dev"
Requires-Dist: pre-commit<5; extra == "dev"
Requires-Dist: autoflake<2; extra == "dev"
Provides-Extra: test
Requires-Dist: pytest<9,>=8.3.2; extra == "test"
Requires-Dist: pytest-cov<6,>=5.0.0; extra == "test"
Requires-Dist: pytest-asyncio<2; extra == "test"
Requires-Dist: httpx<1,>=0.28.1; extra == "test"
Provides-Extra: aws
Requires-Dist: boto3>=1.42.26; extra == "aws"
Provides-Extra: azure
Requires-Dist: azure-identity>=1.25.1; extra == "azure"
Requires-Dist: azure-keyvault-secrets>=4.10.0; extra == "azure"
Provides-Extra: vault
Requires-Dist: hvac>=2.4.0; extra == "vault"
Provides-Extra: cloud
Requires-Dist: boto3>=1.42.26; extra == "cloud"
Requires-Dist: azure-identity>=1.25.1; extra == "cloud"
Requires-Dist: azure-keyvault-secrets>=4.10.0; extra == "cloud"
Requires-Dist: hvac>=2.4.0; extra == "cloud"
Dynamic: license-file
